Metadata-Version: 2.4
Name: campo-estatico-mdf_065
Version: 0.1.0
Summary: Solucionador 2D de la Ecuación de Laplace usando el Método de Diferencias Finitas (MDF) e iteración de Jacobi.
Home-page: https://github.com/Darkenis065/LaplaceSolver
Author: Sebastian Acuña y Jose Luis Zamora
Author-email: jose20022011@hotmail.es
License: GPLv3
Classifier: Development Status :: 3 - Alpha
Classifier: Intended Audience :: Science/Research
Classifier: License :: OSI Approved :: GNU General Public License v3 (GPLv3)
Classifier: Programming Language :: Python :: 3
Classifier: Programming Language :: Python :: 3.9
Classifier: Programming Language :: Python :: 3.10
Requires-Python: >=3.9
License-File: LICENSE
Requires-Dist: numpy>=1.20
Dynamic: author
Dynamic: author-email
Dynamic: classifier
Dynamic: description
Dynamic: description-content-type
Dynamic: home-page
Dynamic: license
Dynamic: license-file
Dynamic: requires-dist
Dynamic: requires-python
Dynamic: summary
